rlpe_AAAI/__init__.py
rlpe_AAAI/rlpe.py
example_pkg_rlpe_AAAI-0.0.1.dist-info/LICENSE
example_pkg_rlpe_AAAI-0.0.1.dist-info/METADATA
example_pkg_rlpe_AAAI-0.0.1.dist-info/WHEEL
example_pkg_rlpe_AAAI-0.0.1.dist-info/top_level.txt
example_pkg_rlpe_AAAI-0.0.1.dist-info/RECORD
