Metadata-Version: 2.1
Name: example-pkg-rlpe-AAAI
Version: 0.0.1
Summary: An example for the paper "Reinforcement Learning Exaplainability via Model Transforms" for AAAI conference
Home-page: https://github.com/MiraFinkel/marl_transforms.git
Author: Mira
Author-email: mirafinkel@gmail.com
License: UNKNOWN
Project-URL: Bug Tracker, https://github.com/MiraFinkel/marl_transforms.git
Platform: UNKNOWN
Classifier: Programming Language :: Python :: 3
Classifier: License :: OSI Approved :: MIT License
Classifier: Operating System :: OS Independent
Requires-Python: >=3.6
License-File: LICENSE
